unipile_sdk/__init__.py
unipile_sdk/api_endpoints.py
unipile_sdk/client.py
unipile_sdk/errors.py
unipile_sdk/helpers.py
unipile_sdk/logging.py
unipile_sdk/typing.py
unipile_sdk/models/__init__.py
unipile_sdk/models/account.py
unipile_sdk/models/chat.py
unipile_sdk/models/common.py
unipile_sdk/models/error.py
unipile_sdk/models/search.py
unipile_sdk/models/user.py
i_unipile_sdk-0.3.4a1.dist-info/METADATA
i_unipile_sdk-0.3.4a1.dist-info/WHEEL
i_unipile_sdk-0.3.4a1.dist-info/top_level.txt
i_unipile_sdk-0.3.4a1.dist-info/RECORD
