Metadata-Version: 2.4
Name: i-unipile-sdk
Version: 0.3.4a1
Summary: Python SDK for interacting with Unipile API.
Requires-Python: >=3.10
Requires-Dist: httpx>=0.28.1
Requires-Dist: pydantic>=2.10.6
